filum/__init__.py
filum/__main__.py
filum/archiver.py
filum/cli.py
filum/config.py
filum/controller.py
filum/database.py
filum/download.py
filum/exceptions.py
filum/helpers.py
filum/operations.py
filum/parser.py
filum/validation.py
filum/view.py
filum/parsers/__init__.py
filum/parsers/parse_hn.py
filum/parsers/parse_reddit.py
filum/parsers/parse_se.py
logger/__init__.py
logger/logger.py
filum-0.1.0.dist-info/LICENSE
filum-0.1.0.dist-info/METADATA
filum-0.1.0.dist-info/WHEEL
filum-0.1.0.dist-info/entry_points.txt
filum-0.1.0.dist-info/top_level.txt
filum-0.1.0.dist-info/RECORD
