Metadata-Version: 2.1
Name: filum
Version: 0.1.0
Summary: A tool to create a local archive of discussion threads
Home-page: https://github.com/PizzaMyHeart/filum
Author: Ian Tan
Classifier: Programming Language :: Python :: 3
Classifier: License :: OSI Approved :: MIT License
Classifier: Operating System :: POSIX :: Linux
Classifier: Development Status :: 3 - Alpha
Classifier: Environment :: Console
Requires-Python: >=3
License-File: LICENSE
Requires-Dist: beautifulsoup4
Requires-Dist: certifi
Requires-Dist: charset-normalizer
Requires-Dist: commonmark
Requires-Dist: html5lib
Requires-Dist: idna
Requires-Dist: markdownify
Requires-Dist: Pygments
Requires-Dist: requests
Requires-Dist: rich
Requires-Dist: six
Requires-Dist: soupsieve
Requires-Dist: typing-extensions
Requires-Dist: urllib3
Requires-Dist: webencodings
